README.rst
setup.py
approx_dates/__init__.py
approx_dates/models.py
approx_dates.egg-info/PKG-INFO
approx_dates.egg-info/SOURCES.txt
approx_dates.egg-info/dependency_links.txt
approx_dates.egg-info/requires.txt
approx_dates.egg-info/top_level.txt
approx_dates/tests/__init__.py
approx_dates/tests/test_creation.py
approx_dates/tests/test_equality.py
approx_dates/tests/test_range.py
approx_dates/tests/test_repr.py