Metadata-Version: 1.0
Name: approx-dates
Version: 0.0.1
Summary: Classes for representing partial and approximate dates
Home-page: UNKNOWN
Author: Mark Longair
Author-email: mark@mysociety.org
License: MIT
Keywords: dates
Platform: UNKNOWN
